flask_restful_extend/json_encode_manager.py
flask_restful_extend/__init__.py
flask_restful_extend/model_reqparse.py
flask_restful_extend/model_validates.py
flask_restful_extend/marshal.py
flask_restful_extend/error_handling.py
flask_restful_extend/extend_json.py
flask_restful_extend/model_converter.py
flask_restful_extend/reqparse_fixed_type.py
Flask_RESTful_extend-0.3.7.dist-info/metadata.json
Flask_RESTful_extend-0.3.7.dist-info/METADATA
Flask_RESTful_extend-0.3.7.dist-info/RECORD
Flask_RESTful_extend-0.3.7.dist-info/top_level.txt
Flask_RESTful_extend-0.3.7.dist-info/WHEEL
Flask_RESTful_extend-0.3.7.dist-info/DESCRIPTION.rst
