Metadata-Version: 2.0
Name: Flask-RESTful-extend
Version: 0.3.7
Summary: Improve Flask-RESTFul's behavior. Add some new features.
Home-page: https://github.com/anjianshi/flask-restful-extend
Author: anjianshi
Author-email: anjianshi@gmail.com
License: MIT
Keywords: flask,python,rest,api
Platform: any
Classifier: Intended Audience :: Developers
Classifier: License :: OSI Approved :: MIT License
Classifier: Operating System :: OS Independent
Classifier: Programming Language :: Python
Classifier: Programming Language :: Python :: 2.7
Requires-Dist: Flask (>=0.10)
Requires-Dist: Flask-RESTful (>=0.3)
Requires-Dist: Flask-SQLAlchemy
Requires-Dist: six
Requires-Dist: json-encode-manager
